wordtrie/VERSION
wordtrie/__init__.py
wordtrie-0.0.4.dist-info/LICENSE
wordtrie-0.0.4.dist-info/METADATA
wordtrie-0.0.4.dist-info/WHEEL
wordtrie-0.0.4.dist-info/top_level.txt
wordtrie-0.0.4.dist-info/RECORD
